odoo/addons/mrp_bom_line_formula_quantity/README.rst
odoo/addons/mrp_bom_line_formula_quantity/__init__.py
odoo/addons/mrp_bom_line_formula_quantity/__manifest__.py
odoo/addons/mrp_bom_line_formula_quantity/i18n/hr.po
odoo/addons/mrp_bom_line_formula_quantity/i18n/it.po
odoo/addons/mrp_bom_line_formula_quantity/i18n/mrp_bom_line_formula_quantity.pot
odoo/addons/mrp_bom_line_formula_quantity/i18n/nl.po
odoo/addons/mrp_bom_line_formula_quantity/i18n/pt_BR.po
odoo/addons/mrp_bom_line_formula_quantity/models/__init__.py
odoo/addons/mrp_bom_line_formula_quantity/models/mrp_bom_line.py
odoo/addons/mrp_bom_line_formula_quantity/models/mrp_production.py
odoo/addons/mrp_bom_line_formula_quantity/readme/CONFIGURE.md
odoo/addons/mrp_bom_line_formula_quantity/readme/DESCRIPTION.md
odoo/addons/mrp_bom_line_formula_quantity/readme/USAGE.md
odoo/addons/mrp_bom_line_formula_quantity/static/description/icon.png
odoo/addons/mrp_bom_line_formula_quantity/static/description/index.html
odoo/addons/mrp_bom_line_formula_quantity/static/description/images/bom.png
odoo/addons/mrp_bom_line_formula_quantity/static/description/images/product_attribute.png
odoo/addons/mrp_bom_line_formula_quantity/static/description/images/product_tab_attributes.png
odoo/addons/mrp_bom_line_formula_quantity/static/description/images/production_order.png
odoo/addons/mrp_bom_line_formula_quantity/static/description/images/sale_order.png
odoo/addons/mrp_bom_line_formula_quantity/static/description/images/website_sale_product.png
odoo/addons/mrp_bom_line_formula_quantity/tests/__init__.py
odoo/addons/mrp_bom_line_formula_quantity/tests/test_mrp_bom_line.py
odoo/addons/mrp_bom_line_formula_quantity/tests/test_mrp_production.py
odoo/addons/mrp_bom_line_formula_quantity/views/mrp_bom_line_views.xml
odoo/addons/mrp_bom_line_formula_quantity/views/mrp_bom_views.xml
odoo_addon_mrp_bom_line_formula_quantity-18.0.1.0.0.3.dist-info/METADATA
odoo_addon_mrp_bom_line_formula_quantity-18.0.1.0.0.3.dist-info/WHEEL
odoo_addon_mrp_bom_line_formula_quantity-18.0.1.0.0.3.dist-info/top_level.txt
odoo_addon_mrp_bom_line_formula_quantity-18.0.1.0.0.3.dist-info/RECORD
