Metadata-Version: 2.1
Name: odoo-addon-mrp_bom_line_formula_quantity
Version: 18.0.1.0.0.3
Requires-Python: >=3.10
Requires-Dist: odoo==18.0.*
Summary: Compute the quantity of a Production Line using a formula in the BoM Line.
Home-page: https://github.com/OCA/manufacture/list/16.0/mrp_bom_line_formula_quantity
License: AGPL-3
Author: Aion Tech, Odoo Community Association (OCA)
Author-email: support@odoo-community.org
Classifier: Programming Language :: Python
Classifier: Framework :: Odoo
Classifier: Framework :: Odoo :: 18.0
Classifier: License :: OSI Approved :: GNU Affero General Public License v3
